{
  "resolvedId": "/workspace/Kubernetes-Bootcamp/node_modules/@nuxt-themes/elements/components/globals/VideoPlayer.vue?vue&type=style&index=0&scoped=cfa5f079&transformed=true&lang.postcss",
  "transforms": [
    {
      "name": "pinceau-transforms",
      "result": ".video-player{position:relative;display:inline-block;margin-top:var(--space-8);margin-bottom:var(--space-8);overflow:hidden;background:var(--color-gray-900);border-radius:var(--radii-lg);}.video-player .loaded{position:absolute;top:0;inset-inline-start:0;width:100%;height:100%;}.video-player video{width:100%;}.video-player iframe{width:100%;height:100%;}.video-player .play-button{position:absolute;top:0;inset-inline-start:0;width:100%;height:100%;cursor:pointer;}.video-player .play-button button{position:absolute;transform:translate3d(-50%, -50%, 0);top:50%;inset-inline-start:50%;z-index:1;width:var(--space-24);height:var(--space-24);filter:grayscale(100%);transition:filter 0.1s cubic-bezier(0, 0, 0.2, 1);background-position:center;background-repeat:no-repeat;background-color:transparent;background-image:url('data:image/svg+xml;utf8,<svg xmlns=\"http://www.w3.org/2000/svg\" version=\"1.1\" viewBox=\"0 0 68 48\"><path fill=\"%23f00\" fill-opacity=\"0.8\" d=\"M66.52,7.74c-0.78-2.93-2.49-5.41-5.42-6.19C55.79,.13,34,0,34,0S12.21,.13,6.9,1.55 C3.97,2.33,2.27,4.81,1.48,7.74C0.06,13.05,0,24,0,24s0.06,10.95,1.48,16.26c0.78,2.93,2.49,5.41,5.42,6.19 C12.21,47.87,34,48,34,48s21.79-0.13,27.1-1.55c2.93-0.78,4.64-3.26,5.42-6.19C67.94,34.95,68,24,68,24S67.94,13.05,66.52,7.74z\"></path><path d=\"M 45,24 27,14 27,34\" fill=\"%23fff\"></path></svg>');}.video-player .play-button:hover button{filter:none;}",
      "start": 1708974340580,
      "end": 1708974340583,
      "sourcemaps": {
        "version": 3,
        "file": "/workspace/Kubernetes-Bootcamp/node_modules/@nuxt-themes/elements/components/globals/VideoPlayer.vue",
        "sources": [
          "/workspace/Kubernetes-Bootcamp/node_modules/@nuxt-themes/elements/components/globals/VideoPlayer.vue"
        ],
        "sourcesContent": [
          ".video-player{position:relative;display:inline-block;margin-top:var(--space-8);margin-bottom:var(--space-8);overflow:hidden;background:var(--color-gray-900);border-radius:var(--radii-lg);}.video-player .loaded{position:absolute;top:0;inset-inline-start:0;width:100%;height:100%;}.video-player video{width:100%;}.video-player iframe{width:100%;height:100%;}.video-player .play-button{position:absolute;top:0;inset-inline-start:0;width:100%;height:100%;cursor:pointer;}.video-player .play-button button{position:absolute;transform:translate3d(-50%, -50%, 0);top:50%;inset-inline-start:50%;z-index:1;width:var(--space-24);height:var(--space-24);filter:grayscale(100%);transition:filter 0.1s cubic-bezier(0, 0, 0.2, 1);background-position:center;background-repeat:no-repeat;background-color:transparent;background-image:url('data:image/svg+xml;utf8,<svg xmlns=\"http://www.w3.org/2000/svg\" version=\"1.1\" viewBox=\"0 0 68 48\"><path fill=\"%23f00\" fill-opacity=\"0.8\" d=\"M66.52,7.74c-0.78-2.93-2.49-5.41-5.42-6.19C55.79,.13,34,0,34,0S12.21,.13,6.9,1.55 C3.97,2.33,2.27,4.81,1.48,7.74C0.06,13.05,0,24,0,24s0.06,10.95,1.48,16.26c0.78,2.93,2.49,5.41,5.42,6.19 C12.21,47.87,34,48,34,48s21.79-0.13,27.1-1.55c2.93-0.78,4.64-3.26,5.42-6.19C67.94,34.95,68,24,68,24S67.94,13.05,66.52,7.74z\"></path><path d=\"M 45,24 27,14 27,34\" fill=\"%23fff\"></path></svg>');}.video-player .play-button:hover button{filter:none;}"
        ],
        "names": [],
        "mappings": "AAAA"
      }
    },
    {
      "name": "nuxt:layer-aliasing",
      "start": 1708974340583,
      "end": 1708974340583,
      "order": "pre"
    },
    {
      "name": "nuxt:layer-aliasing",
      "start": 1708974340583,
      "end": 1708974340583,
      "order": "pre"
    },
    {
      "name": "nuxt:server-devonly:transform",
      "start": 1708974340583,
      "end": 1708974340583,
      "order": "pre"
    },
    {
      "name": "nuxt:server-devonly:transform",
      "start": 1708974340583,
      "end": 1708974340583,
      "order": "pre"
    },
    {
      "name": "pinceau-transforms",
      "result": ".video-player{position:relative;display:inline-block;margin-top:var(--space-8);margin-bottom:var(--space-8);overflow:hidden;background:var(--color-gray-900);border-radius:var(--radii-lg);}.video-player .loaded{position:absolute;top:0;inset-inline-start:0;width:100%;height:100%;}.video-player video{width:100%;}.video-player iframe{width:100%;height:100%;}.video-player .play-button{position:absolute;top:0;inset-inline-start:0;width:100%;height:100%;cursor:pointer;}.video-player .play-button button{position:absolute;transform:translate3d(-50%, -50%, 0);top:50%;inset-inline-start:50%;z-index:1;width:var(--space-24);height:var(--space-24);filter:grayscale(100%);transition:filter 0.1s cubic-bezier(0, 0, 0.2, 1);background-position:center;background-repeat:no-repeat;background-color:transparent;background-image:url('data:image/svg+xml;utf8,<svg xmlns=\"http://www.w3.org/2000/svg\" version=\"1.1\" viewBox=\"0 0 68 48\"><path fill=\"%23f00\" fill-opacity=\"0.8\" d=\"M66.52,7.74c-0.78-2.93-2.49-5.41-5.42-6.19C55.79,.13,34,0,34,0S12.21,.13,6.9,1.55 C3.97,2.33,2.27,4.81,1.48,7.74C0.06,13.05,0,24,0,24s0.06,10.95,1.48,16.26c0.78,2.93,2.49,5.41,5.42,6.19 C12.21,47.87,34,48,34,48s21.79-0.13,27.1-1.55c2.93-0.78,4.64-3.26,5.42-6.19C67.94,34.95,68,24,68,24S67.94,13.05,66.52,7.74z\"></path><path d=\"M 45,24 27,14 27,34\" fill=\"%23fff\"></path></svg>');}.video-player .play-button:hover button{filter:none;}",
      "start": 1708974340583,
      "end": 1708974340583,
      "order": "pre"
    },
    {
      "name": "pinceau-transforms",
      "result": ".video-player{position:relative;display:inline-block;margin-top:var(--space-8);margin-bottom:var(--space-8);overflow:hidden;background:var(--color-gray-900);border-radius:var(--radii-lg);}.video-player .loaded{position:absolute;top:0;inset-inline-start:0;width:100%;height:100%;}.video-player video{width:100%;}.video-player iframe{width:100%;height:100%;}.video-player .play-button{position:absolute;top:0;inset-inline-start:0;width:100%;height:100%;cursor:pointer;}.video-player .play-button button{position:absolute;transform:translate3d(-50%, -50%, 0);top:50%;inset-inline-start:50%;z-index:1;width:var(--space-24);height:var(--space-24);filter:grayscale(100%);transition:filter 0.1s cubic-bezier(0, 0, 0.2, 1);background-position:center;background-repeat:no-repeat;background-color:transparent;background-image:url('data:image/svg+xml;utf8,<svg xmlns=\"http://www.w3.org/2000/svg\" version=\"1.1\" viewBox=\"0 0 68 48\"><path fill=\"%23f00\" fill-opacity=\"0.8\" d=\"M66.52,7.74c-0.78-2.93-2.49-5.41-5.42-6.19C55.79,.13,34,0,34,0S12.21,.13,6.9,1.55 C3.97,2.33,2.27,4.81,1.48,7.74C0.06,13.05,0,24,0,24s0.06,10.95,1.48,16.26c0.78,2.93,2.49,5.41,5.42,6.19 C12.21,47.87,34,48,34,48s21.79-0.13,27.1-1.55c2.93-0.78,4.64-3.26,5.42-6.19C67.94,34.95,68,24,68,24S67.94,13.05,66.52,7.74z\"></path><path d=\"M 45,24 27,14 27,34\" fill=\"%23fff\"></path></svg>');}.video-player .play-button:hover button{filter:none;}",
      "start": 1708974340583,
      "end": 1708974340584,
      "order": "pre"
    },
    {
      "name": "content-slot",
      "start": 1708974340584,
      "end": 1708974340584,
      "order": "pre"
    },
    {
      "name": "content-slot",
      "start": 1708974340584,
      "end": 1708974340584,
      "order": "pre"
    },
    {
      "name": "nuxt:client-fallback-auto-id",
      "start": 1708974340584,
      "end": 1708974340584,
      "order": "pre"
    },
    {
      "name": "vite:css",
      "result": ".video-player{background:var(--color-gray-900);border-radius:var(--radii-lg);display:inline-block;margin-bottom:var(--space-8);margin-top:var(--space-8);overflow:hidden;position:relative}.video-player .loaded{height:100%;inset-inline-start:0;position:absolute;top:0;width:100%}.video-player video{width:100%}.video-player iframe{height:100%;width:100%}.video-player .play-button{cursor:pointer;height:100%;inset-inline-start:0;position:absolute;top:0;width:100%}.video-player .play-button button{background-color:transparent;background-image:url('data:image/svg+xml;utf8,<svg xmlns=\"http://www.w3.org/2000/svg\" version=\"1.1\" viewBox=\"0 0 68 48\"><path fill=\"%23f00\" fill-opacity=\"0.8\" d=\"M66.52,7.74c-0.78-2.93-2.49-5.41-5.42-6.19C55.79,.13,34,0,34,0S12.21,.13,6.9,1.55 C3.97,2.33,2.27,4.81,1.48,7.74C0.06,13.05,0,24,0,24s0.06,10.95,1.48,16.26c0.78,2.93,2.49,5.41,5.42,6.19 C12.21,47.87,34,48,34,48s21.79-0.13,27.1-1.55c2.93-0.78,4.64-3.26,5.42-6.19C67.94,34.95,68,24,68,24S67.94,13.05,66.52,7.74z\"></path><path d=\"M 45,24 27,14 27,34\" fill=\"%23fff\"></path></svg>');background-position:50%;background-repeat:no-repeat;filter:grayscale(100%);height:var(--space-24);inset-inline-start:50%;position:absolute;top:50%;transform:translate3d(-50%,-50%,0);transition:filter .1s cubic-bezier(0,0,.2,1);width:var(--space-24);z-index:1}.video-player .play-button:hover button{filter:none}",
      "start": 1708974340584,
      "end": 1708974340603,
      "order": "normal",
      "sourcemaps": {
        "file": "/workspace/Kubernetes-Bootcamp/node_modules/@nuxt-themes/elements/components/globals/VideoPlayer.vue",
        "mappings": "AAAA,cAA4H,gCAAgC,CAAC,6BAA6B,CAA1J,oBAAoB,CAA2B,4BAA4B,CAAtD,yBAAyB,CAA8B,eAAe,CAA7G,iBAA6K,CAAC,sBAA8E,WAAW,CAA3C,oBAAoB,CAA5C,iBAAiB,CAAC,KAAK,CAAsB,UAAuB,CAAC,oBAAoB,UAAW,CAAC,qBAAgC,WAAW,CAAtB,UAAuB,CAAC,2BAA+F,cAAc,CAA1B,WAAW,CAA3C,oBAAoB,CAA5C,iBAAiB,CAAC,KAAK,CAAsB,UAAsC,CAAC,kCAA+S,4BAA4B,CAAC,2hBAA2hB,CAA/mB,uBAA0B,CAAC,2BAA2B,CAA/H,sBAAsB,CAA7C,sBAAsB,CAA7E,sBAAsB,CAArF,iBAAiB,CAAsC,OAAO,CAA5C,kCAAoC,CAA8G,4CAAiD,CAArH,qBAAqB,CAA/B,SAAgvB,CAAC,wCAAwC,WAAY",
        "names": [],
        "sources": [
          "/workspace/Kubernetes-Bootcamp/node_modules/@nuxt-themes/elements/components/globals/VideoPlayer.vue"
        ],
        "sourcesContent": [
          ".video-player{position:relative;display:inline-block;margin-top:var(--space-8);margin-bottom:var(--space-8);overflow:hidden;background:var(--color-gray-900);border-radius:var(--radii-lg);}.video-player .loaded{position:absolute;top:0;inset-inline-start:0;width:100%;height:100%;}.video-player video{width:100%;}.video-player iframe{width:100%;height:100%;}.video-player .play-button{position:absolute;top:0;inset-inline-start:0;width:100%;height:100%;cursor:pointer;}.video-player .play-button button{position:absolute;transform:translate3d(-50%, -50%, 0);top:50%;inset-inline-start:50%;z-index:1;width:var(--space-24);height:var(--space-24);filter:grayscale(100%);transition:filter 0.1s cubic-bezier(0, 0, 0.2, 1);background-position:center;background-repeat:no-repeat;background-color:transparent;background-image:url('data:image/svg+xml;utf8,<svg xmlns=\"http://www.w3.org/2000/svg\" version=\"1.1\" viewBox=\"0 0 68 48\"><path fill=\"%23f00\" fill-opacity=\"0.8\" d=\"M66.52,7.74c-0.78-2.93-2.49-5.41-5.42-6.19C55.79,.13,34,0,34,0S12.21,.13,6.9,1.55 C3.97,2.33,2.27,4.81,1.48,7.74C0.06,13.05,0,24,0,24s0.06,10.95,1.48,16.26c0.78,2.93,2.49,5.41,5.42,6.19 C12.21,47.87,34,48,34,48s21.79-0.13,27.1-1.55c2.93-0.78,4.64-3.26,5.42-6.19C67.94,34.95,68,24,68,24S67.94,13.05,66.52,7.74z\"></path><path d=\"M 45,24 27,14 27,34\" fill=\"%23fff\"></path></svg>');}.video-player .play-button:hover button{filter:none;}"
        ],
        "version": 3
      }
    },
    {
      "name": "vite:esbuild",
      "start": 1708974340603,
      "end": 1708974340603,
      "order": "normal"
    },
    {
      "name": "vite:json",
      "start": 1708974340603,
      "end": 1708974340603,
      "order": "normal"
    },
    {
      "name": "vite:worker",
      "start": 1708974340603,
      "end": 1708974340603,
      "order": "normal"
    },
    {
      "name": "vite:vue",
      "result": ".video-player[data-v-cfa5f079]{background:var(--color-gray-900);border-radius:var(--radii-lg);display:inline-block;margin-bottom:var(--space-8);margin-top:var(--space-8);overflow:hidden;position:relative}.video-player .loaded[data-v-cfa5f079]{height:100%;inset-inline-start:0;position:absolute;top:0;width:100%}.video-player video[data-v-cfa5f079]{width:100%}.video-player iframe[data-v-cfa5f079]{height:100%;width:100%}.video-player .play-button[data-v-cfa5f079]{cursor:pointer;height:100%;inset-inline-start:0;position:absolute;top:0;width:100%}.video-player .play-button button[data-v-cfa5f079]{background-color:transparent;background-image:url('data:image/svg+xml;utf8,<svg xmlns=\"http://www.w3.org/2000/svg\" version=\"1.1\" viewBox=\"0 0 68 48\"><path fill=\"%23f00\" fill-opacity=\"0.8\" d=\"M66.52,7.74c-0.78-2.93-2.49-5.41-5.42-6.19C55.79,.13,34,0,34,0S12.21,.13,6.9,1.55 C3.97,2.33,2.27,4.81,1.48,7.74C0.06,13.05,0,24,0,24s0.06,10.95,1.48,16.26c0.78,2.93,2.49,5.41,5.42,6.19 C12.21,47.87,34,48,34,48s21.79-0.13,27.1-1.55c2.93-0.78,4.64-3.26,5.42-6.19C67.94,34.95,68,24,68,24S67.94,13.05,66.52,7.74z\"></path><path d=\"M 45,24 27,14 27,34\" fill=\"%23fff\"></path></svg>');background-position:50%;background-repeat:no-repeat;filter:grayscale(100%);height:var(--space-24);inset-inline-start:50%;position:absolute;top:50%;transform:translate3d(-50%,-50%,0);transition:filter .1s cubic-bezier(0,0,.2,1);width:var(--space-24);z-index:1}.video-player .play-button:hover button[data-v-cfa5f079]{filter:none}",
      "start": 1708974340604,
      "end": 1708974340608,
      "order": "normal",
      "sourcemaps": {
        "file": "/workspace/Kubernetes-Bootcamp/node_modules/@nuxt-themes/elements/components/globals/VideoPlayer.vue",
        "mappings": "AAAA,+BAAc,gCAAgC,CAAC,6BAA6B,CAAC,oBAAoB,CAAC,4BAA4B,CAAC,yBAAyB,CAAC,eAAe,CAAC,iBAAiB,CAAC,uCAAsB,WAAW,CAAC,oBAAoB,CAAC,iBAAiB,CAAC,KAAK,CAAC,UAAU,CAAC,qCAAoB,UAAU,CAAC,sCAAqB,WAAW,CAAC,UAAU,CAAC,4CAA2B,cAAc,CAAC,WAAW,CAAC,oBAAoB,CAAC,iBAAiB,CAAC,KAAK,CAAC,UAAU,CAAC,mDAAkC,4BAA4B,CAAC,2hBAA2hB,CAAC,uBAAuB,CAAC,2BAA2B,CAAC,sBAAsB,CAAC,sBAAsB,CAAC,sBAAsB,CAAC,iBAAiB,CAAC,OAAO,CAAC,kCAAkC,CAAC,4CAA4C,CAAC,qBAAqB,CAAC,SAAS,CAAC,yDAAwC,WAAW",
        "names": [],
        "sources": [
          "/workspace/Kubernetes-Bootcamp/node_modules/@nuxt-themes/elements/components/globals/VideoPlayer.vue"
        ],
        "sourcesContent": [
          null
        ],
        "version": 3
      }
    },
    {
      "name": "vite:vue-jsx",
      "start": 1708974340609,
      "end": 1708974340609,
      "order": "normal"
    },
    {
      "name": "replace",
      "start": 1708974340611,
      "end": 1708974340611,
      "order": "normal"
    },
    {
      "name": "replace",
      "start": 1708974340611,
      "end": 1708974340611,
      "order": "normal"
    },
    {
      "name": "nuxt:remove-plugin-metadata",
      "start": 1708974340614,
      "end": 1708974340616,
      "order": "normal"
    },
    {
      "name": "nuxt:remove-plugin-metadata",
      "start": 1708974340614,
      "end": 1708974340616,
      "order": "normal"
    },
    {
      "name": "nuxt:components:imports",
      "start": 1708974340617,
      "end": 1708974340617,
      "order": "normal"
    },
    {
      "name": "replace",
      "start": 1708974340617,
      "end": 1708974340617,
      "order": "normal"
    },
    {
      "name": "ssr-styles",
      "start": 1708974340617,
      "end": 1708974340617,
      "order": "normal"
    },
    {
      "name": "vite:define",
      "start": 1708974340617,
      "end": 1708974340617,
      "order": "normal"
    },
    {
      "name": "vite:css-post",
      "result": "",
      "start": 1708974340617,
      "end": 1708974340620,
      "order": "normal",
      "sourcemaps": {
        "mappings": ""
      }
    },
    {
      "name": "vite:build-html",
      "start": 1708974340621,
      "end": 1708974340621,
      "order": "normal"
    },
    {
      "name": "vite:worker-import-meta-url",
      "start": 1708974340621,
      "end": 1708974340621,
      "order": "normal"
    },
    {
      "name": "vite:asset-import-meta-url",
      "start": 1708974340621,
      "end": 1708974340621,
      "order": "normal"
    },
    {
      "name": "commonjs",
      "start": 1708974340621,
      "end": 1708974340621,
      "order": "normal"
    },
    {
      "name": "vite:dynamic-import-vars",
      "start": 1708974340621,
      "end": 1708974340621,
      "order": "normal"
    },
    {
      "name": "vite:import-glob",
      "start": 1708974340621,
      "end": 1708974340621,
      "order": "normal"
    },
    {
      "name": "nuxt:composable-keys",
      "start": 1708974340621,
      "end": 1708974340621,
      "order": "post"
    },
    {
      "name": "nuxt:composable-keys",
      "start": 1708974340621,
      "end": 1708974340621,
      "order": "post"
    },
    {
      "name": "nuxt:imports-transform",
      "start": 1708974340621,
      "end": 1708974340621,
      "order": "post"
    },
    {
      "name": "nuxt:imports-transform",
      "start": 1708974340621,
      "end": 1708974340621,
      "order": "post"
    },
    {
      "name": "unctx:transform",
      "start": 1708974340621,
      "end": 1708974340621,
      "order": "post"
    },
    {
      "name": "unctx:transform",
      "start": 1708974340621,
      "end": 1708974340621,
      "order": "post"
    },
    {
      "name": "nuxt:pages-macros-transform",
      "start": 1708974340621,
      "end": 1708974340621,
      "order": "post"
    },
    {
      "name": "nuxt:pages-macros-transform",
      "start": 1708974340621,
      "end": 1708974340621,
      "order": "post"
    },
    {
      "name": "nuxt:tree-shake-template",
      "start": 1708974340622,
      "end": 1708974340622,
      "order": "post"
    },
    {
      "name": "nuxt:components-loader",
      "start": 1708974340622,
      "end": 1708974340622,
      "order": "post"
    },
    {
      "name": "nuxt:tree-shake-composables:transform",
      "start": 1708974340622,
      "end": 1708974340622,
      "order": "post"
    },
    {
      "name": "vite:build-import-analysis",
      "start": 1708974340622,
      "end": 1708974340622,
      "order": "normal"
    },
    {
      "name": "vite:reporter",
      "start": 1708974340622,
      "end": 1708974340622,
      "order": "normal"
    }
  ]
}
