[{"_path":"/scale-your-app/lab","_dir":"scale-your-app","_draft":false,"_partial":false,"_locale":"","title":"Lab 05: Scaling Your Application","description":"Welcome to Lab 05! In this session, we'll learn how to efficiently scale your applications using Kubernetes. We'll explore both declarative and imperative methods to give you the tools and understanding needed to manage your app's scalability like a pro.","_type":"markdown","_id":"content:6.Scale-Your-App:2.Lab.md","_source":"content","_file":"6.Scale-Your-App/2.Lab.md","_extension":"md"},{"_path":"/update-your-app/lab","_dir":"update-your-app","_draft":false,"_partial":false,"_locale":"","title":"Lab","description":"","_type":"markdown","_id":"content:7.Update-Your-App:2.Lab.md","_source":"content","_file":"7.Update-Your-App/2.Lab.md","_extension":"md"}]