[{"_path":"/scale-your-app/scale-in-and-out","_dir":"scale-your-app","_draft":false,"_partial":false,"_locale":"","title":"Understanding Scaling","description":"In this module, we delve into scaling your application within a Kubernetes environment. Scaling is a critical aspect of managing applications, ensuring they can handle varying loads of traffic. Kubernetes simplifies this process through Deployments and Services, enabling both scale-out (increasing the number of replicas) and scale-in (decreasing the number of replicas) operations.","_type":"markdown","_id":"content:6.Scale-Your-App:1.scale-In-and-Out.md","_source":"content","_file":"6.Scale-Your-App/1.scale-In-and-Out.md","_extension":"md"},{"_path":"/update-your-app/rolling-up","_dir":"update-your-app","_draft":false,"_partial":false,"_locale":"","title":"Understanding Rolling Updates","description":"Rolling updates are a fundamental feature in Kubernetes, enabling you to update the running version of your application seamlessly and without downtime. This approach is crucial for maintaining continuous availability, meeting the modern expectations of both users and developers for frequent updates.","_type":"markdown","_id":"content:7.Update-Your-App:1.Rolling-up.md","_source":"content","_file":"7.Update-Your-App/1.Rolling-up.md","_extension":"md"}]