{
  "resolvedId": "/workspace/Kubernetes-Bootcamp/node_modules/@nuxt-themes/elements/components/globals/Ellipsis.vue?vue&type=style&index=0&scoped=5fd4c706&transformed=true&lang.postcss",
  "transforms": [
    {
      "name": "pinceau-transforms",
      "result": ".ellipsis{pointer-events:none;position:absolute;top:var(---c-cn-top);inset-inline-start:var(---eih-inset-inline-start);inset-inline-end:var(---if-b-inset-inline-end);z-index:var(---ss-e-z-index);width:-webkit-fill-available;max-width:var(---wj8-max-width);height:var(---t33-height);filter:var(---jfd-filter);}.ellipsis .ellipsis-item{width:100%;height:100%;background:var(---y-uj-background);}",
      "start": 1708210050806,
      "end": 1708210050815,
      "sourcemaps": {
        "version": 3,
        "file": "/workspace/Kubernetes-Bootcamp/node_modules/@nuxt-themes/elements/components/globals/Ellipsis.vue",
        "sources": [
          "/workspace/Kubernetes-Bootcamp/node_modules/@nuxt-themes/elements/components/globals/Ellipsis.vue"
        ],
        "sourcesContent": [
          ".ellipsis{pointer-events:none;position:absolute;top:var(---c-cn-top);inset-inline-start:var(---eih-inset-inline-start);inset-inline-end:var(---if-b-inset-inline-end);z-index:var(---ss-e-z-index);width:-webkit-fill-available;max-width:var(---wj8-max-width);height:var(---t33-height);filter:var(---jfd-filter);}.ellipsis .ellipsis-item{width:100%;height:100%;background:var(---y-uj-background);}"
        ],
        "names": [],
        "mappings": "AAAA"
      }
    },
    {
      "name": "nuxt:layer-aliasing",
      "start": 1708210050815,
      "end": 1708210050815,
      "order": "pre"
    },
    {
      "name": "nuxt:server-devonly:transform",
      "start": 1708210050815,
      "end": 1708210050815,
      "order": "pre"
    },
    {
      "name": "pinceau-transforms",
      "result": ".ellipsis{pointer-events:none;position:absolute;top:var(---c-cn-top);inset-inline-start:var(---eih-inset-inline-start);inset-inline-end:var(---if-b-inset-inline-end);z-index:var(---ss-e-z-index);width:-webkit-fill-available;max-width:var(---wj8-max-width);height:var(---t33-height);filter:var(---jfd-filter);}.ellipsis .ellipsis-item{width:100%;height:100%;background:var(---y-uj-background);}",
      "start": 1708210050815,
      "end": 1708210050815,
      "order": "pre"
    },
    {
      "name": "content-slot",
      "start": 1708210050815,
      "end": 1708210050815,
      "order": "pre"
    },
    {
      "name": "nuxt:client-fallback-auto-id",
      "start": 1708210050815,
      "end": 1708210050815,
      "order": "pre"
    },
    {
      "name": "vite:css",
      "result": ".ellipsis{filter:var(---jfd-filter);height:var(---t33-height);inset-inline-end:var(---if-b-inset-inline-end);inset-inline-start:var(---eih-inset-inline-start);max-width:var(---wj8-max-width);pointer-events:none;position:absolute;top:var(---c-cn-top);width:-webkit-fill-available;z-index:var(---ss-e-z-index)}.ellipsis .ellipsis-item{background:var(---y-uj-background);height:100%;width:100%}",
      "start": 1708210050815,
      "end": 1708210050819,
      "order": "normal",
      "sourcemaps": {
        "mappings": ""
      }
    },
    {
      "name": "vite:esbuild",
      "start": 1708210050819,
      "end": 1708210050819,
      "order": "normal"
    },
    {
      "name": "vite:json",
      "start": 1708210050819,
      "end": 1708210050819,
      "order": "normal"
    },
    {
      "name": "vite:worker",
      "start": 1708210050819,
      "end": 1708210050819,
      "order": "normal"
    },
    {
      "name": "vite:vue",
      "result": ".ellipsis[data-v-5fd4c706]{filter:var(---jfd-filter);height:var(---t33-height);inset-inline-end:var(---if-b-inset-inline-end);inset-inline-start:var(---eih-inset-inline-start);max-width:var(---wj8-max-width);pointer-events:none;position:absolute;top:var(---c-cn-top);width:-webkit-fill-available;z-index:var(---ss-e-z-index)}.ellipsis .ellipsis-item[data-v-5fd4c706]{background:var(---y-uj-background);height:100%;width:100%}",
      "start": 1708210050819,
      "end": 1708210050820,
      "order": "normal",
      "sourcemaps": {
        "mappings": ""
      }
    },
    {
      "name": "vite:vue-jsx",
      "start": 1708210050820,
      "end": 1708210050820,
      "order": "normal"
    },
    {
      "name": "replace",
      "start": 1708210050820,
      "end": 1708210050820,
      "order": "normal"
    },
    {
      "name": "nuxt:remove-plugin-metadata",
      "start": 1708210050820,
      "end": 1708210050820,
      "order": "normal"
    },
    {
      "name": "nuxt:chunk-error",
      "start": 1708210050820,
      "end": 1708210050820,
      "order": "normal"
    },
    {
      "name": "nuxt:components:imports",
      "start": 1708210050820,
      "end": 1708210050820,
      "order": "normal"
    },
    {
      "name": "replace",
      "start": 1708210050820,
      "end": 1708210050820,
      "order": "normal"
    },
    {
      "name": "ssr-styles",
      "start": 1708210050820,
      "end": 1708210050820,
      "order": "normal"
    },
    {
      "name": "vite:define",
      "start": 1708210050820,
      "end": 1708210050820,
      "order": "normal"
    },
    {
      "name": "vite:css-post",
      "result": "",
      "start": 1708210050820,
      "end": 1708210050820,
      "order": "normal",
      "sourcemaps": {
        "mappings": ""
      }
    },
    {
      "name": "vite:build-html",
      "start": 1708210050820,
      "end": 1708210050820,
      "order": "normal"
    },
    {
      "name": "vite:worker-import-meta-url",
      "start": 1708210050820,
      "end": 1708210050820,
      "order": "normal"
    },
    {
      "name": "vite:asset-import-meta-url",
      "start": 1708210050820,
      "end": 1708210050820,
      "order": "normal"
    },
    {
      "name": "commonjs",
      "start": 1708210050820,
      "end": 1708210050820,
      "order": "normal"
    },
    {
      "name": "vite:dynamic-import-vars",
      "start": 1708210050820,
      "end": 1708210050820,
      "order": "normal"
    },
    {
      "name": "vite:import-glob",
      "start": 1708210050820,
      "end": 1708210050820,
      "order": "normal"
    },
    {
      "name": "nuxt:composable-keys",
      "start": 1708210050820,
      "end": 1708210050820,
      "order": "post"
    },
    {
      "name": "nuxt:imports-transform",
      "start": 1708210050820,
      "end": 1708210050820,
      "order": "post"
    },
    {
      "name": "unctx:transform",
      "start": 1708210050820,
      "end": 1708210050820,
      "order": "post"
    },
    {
      "name": "nuxt:pages-macros-transform",
      "start": 1708210050820,
      "end": 1708210050820,
      "order": "post"
    },
    {
      "name": "nuxt:runtime-paths-dep",
      "start": 1708210050820,
      "end": 1708210050820,
      "order": "post"
    },
    {
      "name": "nuxt:route-injection-plugin",
      "start": 1708210050820,
      "end": 1708210050820,
      "order": "post"
    },
    {
      "name": "nuxt:components-loader",
      "start": 1708210050820,
      "end": 1708210050820,
      "order": "post"
    },
    {
      "name": "nuxt:tree-shake-composables:transform",
      "start": 1708210050820,
      "end": 1708210050820,
      "order": "post"
    },
    {
      "name": "vite:build-import-analysis",
      "start": 1708210050820,
      "end": 1708210050820,
      "order": "normal"
    },
    {
      "name": "vite:reporter",
      "start": 1708210050820,
      "end": 1708210050820,
      "order": "normal"
    }
  ]
}
